pptestmateuszlis/__init__.py
pptestmateuszlis/m_mod_pptest.py
pptestmateuszlis-0.0.1.dist-info/License.txt
pptestmateuszlis-0.0.1.dist-info/METADATA
pptestmateuszlis-0.0.1.dist-info/WHEEL
pptestmateuszlis-0.0.1.dist-info/top_level.txt
pptestmateuszlis-0.0.1.dist-info/RECORD
