Metadata-Version: 2.1
Name: pptestmateuszlis
Version: 0.0.1
Summary: My test package
Author-email: ML <matt.lis.1998@gmail.com>
License: MIT License
Keywords: ppmateuszlis,funny functions,name,surname,personal data
Classifier: Environment :: Console
Requires-Python: >=3.0
License-File: License.txt
Requires-Dist: numpy ; python_version >= "3.0"
